Metadata-Version: 2.1
Name: infiniai
Version: 0.0.1
Summary: Computer Vision Helping Library
Home-page: https://github.com/infiniai-tech/infiniai.git
Author: InfiniAi
Author-email: info@infiniai.tech
License: MIT
Keywords: ComputerVision,HandTracking,FaceDetection,PoseEstimation,FaceMesh
Classifier: Programming Language :: Python :: 3
Classifier: License :: OSI Approved :: MIT License
Classifier: Operating System :: OS Independent
Classifier: Programming Language :: Python :: 3.6
Classifier: Programming Language :: Python :: 3.7
Classifier: Programming Language :: Python :: 3.8
Classifier: Programming Language :: Python :: 3.9
Classifier: Programming Language :: Python :: 3.10
License-File: LICENSE
